{
  "main": {
    "id": "d499f14d670611b5",
    "type": "split",
    "children": [
      {
        "id": "38b6985584dc170d",
        "type": "tabs",
        "children": [
          {
            "id": "0b06d0062ba42419",
            "type": "leaf",
            "state": {
              "type": "markdown",
              "state": {
                "file": "writeups/pvg/x009-Sybaris.md",
                "mode": "source",
                "source": false
              }
            }
          },
          {
            "id": "0b1a44d8765b8d43",
            "type": "leaf",
            "state": {
              "type": "markdown",
              "state": {
                "file": "writeups/htb/x001-Chatterbox.md",
                "mode": "source",
                "source": false
              }
            }
          }
        ],
        "currentTab": 1
      }
    ],
    "direction": "vertical"
  },
  "left": {
    "id": "ab027974a2bb2288",
    "type": "split",
    "children": [
      {
        "id": "2e8ec01f074f5975",
        "type": "tabs",
        "children": [
          {
            "id": "d445ce52a43bc5d6",
            "type": "leaf",
            "state": {
              "type": "file-explorer",
              "state": {
                "sortOrder": "alphabetical"
              }
            }
          },
          {
            "id": "d3826124a7706a9b",
            "type": "leaf",
            "state": {
              "type": "search",
              "state": {
                "query": "",
                "matchingCase": false,
                "explainSearch": false,
                "collapseAll": false,
                "extraContext": false,
                "sortOrder": "alphabetical"
              }
            }
          },
          {
            "id": "131fa1b66d0a147c",
            "type": "leaf",
            "state": {
              "type": "starred",
              "state": {}
            }
          }
        ]
      }
    ],
    "direction": "horizontal",
    "width": 312.5
  },
  "right": {
    "id": "7ac301e4eaf8cbac",
    "type": "split",
    "children": [
      {
        "id": "e79380d450e33ad1",
        "type": "tabs",
        "children": [
          {
            "id": "7ab400b562c6387c",
            "type": "leaf",
            "state": {
              "type": "backlink",
              "state": {
                "file": "writeups/htb/x001-Chatterbox.md",
                "collapseAll": false,
                "extraContext": false,
                "sortOrder": "alphabetical",
                "showSearch": false,
                "searchQuery": "",
                "backlinkCollapsed": false,
                "unlinkedCollapsed": true
              }
            }
          },
          {
            "id": "8b84d2d9eceea280",
            "type": "leaf",
            "state": {
              "type": "outgoing-link",
              "state": {
                "file": "writeups/htb/x001-Chatterbox.md",
                "linksCollapsed": false,
                "unlinkedCollapsed": true
              }
            }
          },
          {
            "id": "bb0050d84074e7b3",
            "type": "leaf",
            "state": {
              "type": "tag",
              "state": {
                "sortOrder": "frequency",
                "useHierarchy": true
              }
            }
          },
          {
            "id": "feeb31d83bfc6691",
            "type": "leaf",
            "state": {
              "type": "outline",
              "state": {
                "file": "writeups/htb/x001-Chatterbox.md"
              }
            }
          }
        ]
      }
    ],
    "direction": "horizontal",
    "width": 300,
    "collapsed": true
  },
  "left-ribbon": {
    "hiddenItems": {
      "switcher:Open quick switcher": false,
      "graph:Open graph view": false,
      "canvas:Create new canvas": false,
      "daily-notes:Open today's daily note": false,
      "templates:Insert template": false,
      "command-palette:Open command palette": false
    }
  },
  "active": "0b1a44d8765b8d43",
  "lastOpenFiles": [
    "writeups/htb/index.md",
    "writeups/htb/x001-Chatterbox.md",
    "writeups/pvg/x004-Banzai-Linux.md",
    "writeups/pvg/x006-Wombo.md",
    "writeups/pvg/x009-Sybaris.md",
    "writeups/pvg/x001-ClamAV-Linux.md",
    "writeups/pvg/x002-Born2Root-Linux.md",
    "writeups/pvg/x003-Jacko-Windows.md",
    "writeups/pvg/x005-Zino.md",
    "writeups/pvg/x007-UT99.md",
    "writeups/pvg/x008-Hetemit.md",
    "docs/assets/Pasted image 20230319142322.png",
    "docs/assets/Pasted image 20230319142012.png",
    "docs/assets/Pasted image 20230319141321.png",
    "writeups/pvg/index.md",
    "writeups/index.md",
    "devsecops/SourceCodeAnalysis/index.md",
    "devsecops/index.md",
    "pentesting/ServicePentesting/FTP.md",
    "pentesting/ServicePentesting/index.md",
    "pentesting/index.md",
    "pentesting/ServicePentesting/HTTP(s).md",
    "writeups/pvg/attachments/Pasted image 20220517191508.png",
    "writeups/pvg/attachments/Pasted image 20220301234528.png",
    "writeups/pvg/attachments/Pasted image 20220517191537.png",
    "writeups/pvg/attachments/Pasted image 20220402162115.png",
    "writeups/pvg/attachments/Pasted image 20220515225243.png",
    "writeups/pvg/attachments/Pasted image 20220402162302.png",
    "writeups/pvg/attachments/Pasted image 20220402162514.png",
    "writeups/pvg/attachments",
    "writeups/x009-Sybaris.md",
    "writeups/x008-Hetemit.md",
    "writeups/x007-UT99.md",
    "writeups/x006-Wombo.md",
    "writeups/x005-Zino.md",
    "writeups/x004-Banzai-Linux.md",
    "writeups/attachments",
    "writeups/pvg",
    "writeups/htb copy",
    "writeups/htb",
    "writeups"
  ]
}